pupalink/__init__.py
pupalink/downloader.py
pupalink/metadata.py
pupalink-0.1.0a4.dist-info/LICENSE
pupalink-0.1.0a4.dist-info/WHEEL
pupalink-0.1.0a4.dist-info/METADATA
pupalink-0.1.0a4.dist-info/RECORD
