Metadata-Version: 2.1
Name: pupalink
Version: 0.1.0a4
Summary: Springer Link Download Module for Python
Home-page: https://github.com/pupagang/pupalink
License: GPL-3.0-or-later
Author: Jimmy Nelle
Author-email: jimmy.nelle@hsw-stud.de
Requires-Python: >=3.9,<4.0
Classifier: Development Status :: 3 - Alpha
Classifier: License :: OSI Approved :: GNU General Public License v3 or later (GPLv3+)
Classifier: Operating System :: OS Independent
Classifier: Programming Language :: Python :: 3
Classifier: Programming Language :: Python :: 3.9
Requires-Dist: aiohttp (>=3.7.4,<4.0.0)
Requires-Dist: beautifulsoup4 (>=4.9.3,<5.0.0)
Requires-Dist: lxml (>=4.6.3,<5.0.0)
Project-URL: Repository, https://github.com/pupagang/pupalink
